{
    "DNDConfig": null,
    "__parentReadjusting__": false,
    "_height_": {
        "type": "ref",
        "value": "preferred"
    },
    "_left_": {
        "type": "string",
        "value": "51dp"
    },
    "_margin_": [
        0,
        0,
        0,
        0
    ],
    "_orientation_": 6,
    "_padding_": [
        0,
        0,
        0,
        0
    ],
    "_percent_": true,
    "_skin_": "sbcd86d8ff3148efb42f24d46c08c7ff",
    "_top_": {
        "type": "string",
        "value": "10dp"
    },
    "_width_": {
        "type": "string",
        "value": "100%"
    },
    "allboxes": [],
    "autogrowmode": 1,
    "canUpdateUI": true,
    "centerx": {
        "type": "string",
        "value": "49%"
    },
    "children": [
        "flxRangeContainer",
        "imageupload"
    ],
    "clipbounds": true,
    "containerweight": 100,
    "enablescrolling": true,
    "id": "flxContainer",
    "info": null,
    "iscustomlayout": false,
    "isvisible": false,
    "kuid": "cd16724831474d5cbba6538a0682aa53",
    "layouttype": 2,
    "name": "kony.ui.FlexContainer",
    "parent": "msrmntrange",
    "pf": "userwidgetmodel",
    "retaincontentalignment": false,
    "retainflexpositionproperties": false,
    "snapgridsize": 10,
    "snaptogrid": true,
    "wType": "FlexContainer",
    "widgetalignment": 1,
    "zindex": 1
}